phe/__about__.py
phe/__init__.py
phe/command_line.py
phe/encoding.py
phe/paillier.py
phe/util.py
phe/tests/__init__.py
phe/tests/cli_test.py
phe/tests/math_test.py
phe/tests/paillier_test.py
phe/tests/util_test.py
phe-1.5.0.dist-info/LICENSE.txt
phe-1.5.0.dist-info/METADATA
phe-1.5.0.dist-info/WHEEL
phe-1.5.0.dist-info/entry_points.txt
phe-1.5.0.dist-info/top_level.txt
phe-1.5.0.dist-info/RECORD
