Metadata-Version: 2.1
Name: phe
Version: 1.5.0
Summary: Partially Homomorphic Encryption library for Python
Home-page: https://github.com/data61/python-paillier
Download-URL: https://pypi.python.org/pypi/phe/#downloads
Author: CSIRO's Data61
Author-email: confidential-computing@data61.csiro.au
License: GPLv3
Keywords: cryptography encryption homomorphic
Platform: UNKNOWN
Classifier: License :: OSI Approved :: GNU General Public License v3 (GPLv3)
Classifier: Natural Language :: English
Classifier: Topic :: Scientific/Engineering :: Mathematics
Classifier: Topic :: Security
Classifier: Topic :: Security :: Cryptography
Classifier: Intended Audience :: Science/Research
Classifier: Programming Language :: Python :: 3
Classifier: Programming Language :: Python :: 3.7
Classifier: Programming Language :: Python :: 3.8
Classifier: Programming Language :: Python :: 3.9
Classifier: Programming Language :: Python :: 3.10
Classifier: Programming Language :: Python :: 3.11
Provides-Extra: cli
Provides-Extra: examples
License-File: LICENSE.txt
